{ "SolutionInfo": { "Status": 2, "Runtime": 7.3126173019409180e+01, "Work": 6.0261123464354441e+01, "ObjVal": -47.625, "ObjBound": -47.625, "ObjBoundC": -47.625, "MIPGap": 0, "IntVio": 0, "BoundVio": 0, "ConstrVio": 1.1102230246251565e-16, "IterCount": 315290, "BarIterCount": 0, "NodeCount": 7828, "SolCount": 10, "PoolObjBound": -47.625, "PoolObjVal": [ -47.625, -45.75, -45.625, -44.375, -44, -44, -41.75, -41.75, -37.5, -30.5]}, "Vars": [ { "VarName": "x[16]", "X": 1}, { "VarName": "y[16]", "X": 1}, { "VarName": "y[17]", "X": 1}, { "VarName": "y[18]", "X": 1}, { "VarName": "y[19]", "X": 1}, { "VarName": "y[20]", "X": 1}, { "VarName": "y[21]", "X": 1}, { "VarName": "y[22]", "X": 1}, { "VarName": "y[23]", "X": 1}, { "VarName": "y[24]", "X": 1}, { "VarName": "y[25]", "X": 1}, { "VarName": "y[26]", "X": 1}, { "VarName": "y[27]", "X": 1}, { "VarName": "e[24]", "X": 1}, { "VarName": "r[20]", "X": 1}, { "VarName": "r[23]", "X": 1}, { "VarName": "r[360]", "X": 1}, { "VarName": "r[696]", "X": 1}, { "VarName": "m[16]", "X": 1}, { "VarName": "m[354]", "X": 1}, { "VarName": "m[691]", "X": 1}, { "VarName": "m[1025]", "X": 1}, { "VarName": "m[1367]", "X": 1}, { "VarName": "m[1700]", "X": 1}, { "VarName": "m[2712]", "X": 1}, { "VarName": "z[16]", "X": 1}, { "VarName": "z[17]", "X": 1}, { "VarName": "z[18]", "X": 1}, { "VarName": "z[19]", "X": 1}, { "VarName": "z[20]", "X": 1}, { "VarName": "z[21]", "X": 1}, { "VarName": "z[22]", "X": 1}, { "VarName": "z[23]", "X": 1}, { "VarName": "z[24]", "X": 1}, { "VarName": "z[25]", "X": 1}, { "VarName": "z[26]", "X": 1}, { "VarName": "z[27]", "X": 1}, { "VarName": "z[28]", "X": 1}, { "VarName": "z[29]", "X": 1}, { "VarName": "z[30]", "X": 1}, { "VarName": "z[31]", "X": 1}, { "VarName": "z[32]", "X": 1}, { "VarName": "z[33]", "X": 1}, { "VarName": "z[34]", "X": 1}, { "VarName": "z[35]", "X": 1}, { "VarName": "z[36]", "X": 1}, { "VarName": "z[37]", "X": 1}, { "VarName": "z[38]", "X": 1}, { "VarName": "z[39]", "X": 1}, { "VarName": "z[40]", "X": 1}, { "VarName": "z[41]", "X": 1}, { "VarName": "z[42]", "X": 1}, { "VarName": "z[43]", "X": 1}, { "VarName": "z[44]", "X": 1}, { "VarName": "z[45]", "X": 1}, { "VarName": "z[46]", "X": 1}, { "VarName": "z[47]", "X": 1}, { "VarName": "z[48]", "X": 1}, { "VarName": "z[49]", "X": 1}, { "VarName": "z[50]", "X": 1}, { "VarName": "z[51]", "X": 1}, { "VarName": "z[52]", "X": 1}, { "VarName": "z[53]", "X": 1}, { "VarName": "z[54]", "X": 1}, { "VarName": "z[55]", "X": 1}, { "VarName": "z[56]", "X": 1}, { "VarName": "z[57]", "X": 1}, { "VarName": "z[58]", "X": 1}, { "VarName": "z[59]", "X": 1}, { "VarName": "z[60]", "X": 1}, { "VarName": "z[61]", "X": 1}, { "VarName": "z[62]", "X": 1}, { "VarName": "z[63]", "X": 1}, { "VarName": "z[64]", "X": 1}, { "VarName": "z[65]", "X": 1}, { "VarName": "z[66]", "X": 1}, { "VarName": "z[67]", "X": 1}, { "VarName": "z[68]", "X": 1}, { "VarName": "z[69]", "X": 1}, { "VarName": "z[70]", "X": 1}, { "VarName": "z[71]", "X": 1}, { "VarName": "z[72]", "X": 1}, { "VarName": "z[73]", "X": 1}, { "VarName": "z[74]", "X": 1}, { "VarName": "z[75]", "X": 1}, { "VarName": "z[76]", "X": 1}, { "VarName": "z[77]", "X": 1}, { "VarName": "z[78]", "X": 1}, { "VarName": "z[79]", "X": 1}, { "VarName": "z[80]", "X": 1}, { "VarName": "z[81]", "X": 1}, { "VarName": "z[82]", "X": 1}, { "VarName": "z[83]", "X": 1}, { "VarName": "z[84]", "X": 1}, { "VarName": "z[85]", "X": 1}, { "VarName": "z[86]", "X": 1}, { "VarName": "z[87]", "X": 1}, { "VarName": "z[88]", "X": 1}, { "VarName": "z[89]", "X": 1}, { "VarName": "z[90]", "X": 1}, { "VarName": "z[91]", "X": 1}, { "VarName": "z[92]", "X": 1}, { "VarName": "z[93]", "X": 1}, { "VarName": "z[94]", "X": 1}, { "VarName": "z[95]", "X": 1}, { "VarName": "z[96]", "X": 1}, { "VarName": "z[97]", "X": 1}, { "VarName": "z[98]", "X": 1}, { "VarName": "z[99]", "X": 1}, { "VarName": "z[100]", "X": 1}, { "VarName": "z[101]", "X": 1}, { "VarName": "z[102]", "X": 1}, { "VarName": "z[103]", "X": 1}, { "VarName": "z[104]", "X": 1}, { "VarName": "z[105]", "X": 1}, { "VarName": "z[106]", "X": 1}, { "VarName": "z[107]", "X": 1}, { "VarName": "z[108]", "X": 1}, { "VarName": "z[109]", "X": 1}, { "VarName": "z[110]", "X": 1}, { "VarName": "z[111]", "X": 1}, { "VarName": "z[112]", "X": 1}, { "VarName": "z[113]", "X": 1}, { "VarName": "z[114]", "X": 1}, { "VarName": "z[115]", "X": 1}, { "VarName": "z[116]", "X": 1}, { "VarName": "z[117]", "X": 1}, { "VarName": "z[118]", "X": 1}, { "VarName": "z[119]", "X": 1}, { "VarName": "z[120]", "X": 1}, { "VarName": "z[121]", "X": 1}, { "VarName": "z[122]", "X": 1}, { "VarName": "z[123]", "X": 1}, { "VarName": "z[124]", "X": 1}, { "VarName": "z[354]", "X": 1}, { "VarName": "z[355]", "X": 1}, { "VarName": "z[356]", "X": 1}, { "VarName": "z[357]", "X": 1}, { "VarName": "z[358]", "X": 1}, { "VarName": "z[359]", "X": 1}, { "VarName": "z[360]", "X": 1}, { "VarName": "z[361]", "X": 1}, { "VarName": "z[362]", "X": 1}, { "VarName": "z[363]", "X": 1}, { "VarName": "z[364]", "X": 1}, { "VarName": "z[365]", "X": 1}, { "VarName": "z[366]", "X": 1}, { "VarName": "z[367]", "X": 1}, { "VarName": "z[368]", "X": 1}, { "VarName": "z[369]", "X": 1}, { "VarName": "z[370]", "X": 1}, { "VarName": "z[371]", "X": 1}, { "VarName": "z[372]", "X": 1}, { "VarName": "z[373]", "X": 1}, { "VarName": "z[374]", "X": 1}, { "VarName": "z[375]", "X": 1}, { "VarName": "z[376]", "X": 1}, { "VarName": "z[377]", "X": 1}, { "VarName": "z[378]", "X": 1}, { "VarName": "z[379]", "X": 1}, { "VarName": "z[380]", "X": 1}, { "VarName": "z[381]", "X": 1}, { "VarName": "z[382]", "X": 1}, { "VarName": "z[383]", "X": 1}, { "VarName": "z[384]", "X": 1}, { "VarName": "z[385]", "X": 1}, { "VarName": "z[386]", "X": 1}, { "VarName": "z[387]", "X": 1}, { "VarName": "z[388]", "X": 1}, { "VarName": "z[389]", "X": 1}, { "VarName": "z[390]", "X": 1}, { "VarName": "z[391]", "X": 1}, { "VarName": "z[392]", "X": 1}, { "VarName": "z[393]", "X": 1}, { "VarName": "z[394]", "X": 1}, { "VarName": "z[395]", "X": 1}, { "VarName": "z[396]", "X": 1}, { "VarName": "z[397]", "X": 1}, { "VarName": "z[398]", "X": 1}, { "VarName": "z[399]", "X": 1}, { "VarName": "z[400]", "X": 1}, { "VarName": "z[401]", "X": 1}, { "VarName": "z[402]", "X": 1}, { "VarName": "z[403]", "X": 1}, { "VarName": "z[404]", "X": 1}, { "VarName": "z[405]", "X": 1}, { "VarName": "z[406]", "X": 1}, { "VarName": "z[407]", "X": 1}, { "VarName": "z[408]", "X": 1}, { "VarName": "z[409]", "X": 1}, { "VarName": "z[410]", "X": 1}, { "VarName": "z[411]", "X": 1}, { "VarName": "z[412]", "X": 1}, { "VarName": "z[413]", "X": 1}, { "VarName": "z[414]", "X": 1}, { "VarName": "z[415]", "X": 1}, { "VarName": "z[416]", "X": 1}, { "VarName": "z[417]", "X": 1}, { "VarName": "z[418]", "X": 1}, { "VarName": "z[419]", "X": 1}, { "VarName": "z[420]", "X": 1}, { "VarName": "z[421]", "X": 1}, { "VarName": "z[422]", "X": 1}, { "VarName": "z[423]", "X": 1}, { "VarName": "z[424]", "X": 1}, { "VarName": "z[425]", "X": 1}, { "VarName": "z[426]", "X": 1}, { "VarName": "z[427]", "X": 1}, { "VarName": "z[428]", "X": 1}, { "VarName": "z[429]", "X": 1}, { "VarName": "z[430]", "X": 1}, { "VarName": "z[431]", "X": 1}, { "VarName": "z[432]", "X": 1}, { "VarName": "z[433]", "X": 1}, { "VarName": "z[434]", "X": 1}, { "VarName": "z[435]", "X": 1}, { "VarName": "z[436]", "X": 1}, { "VarName": "z[437]", "X": 1}, { "VarName": "z[438]", "X": 1}, { "VarName": "z[439]", "X": 1}, { "VarName": "z[440]", "X": 1}, { "VarName": "z[441]", "X": 1}, { "VarName": "z[442]", "X": 1}, { "VarName": "z[443]", "X": 1}, { "VarName": "z[444]", "X": 1}, { "VarName": "z[445]", "X": 1}, { "VarName": "z[446]", "X": 1}, { "VarName": "z[447]", "X": 1}, { "VarName": "z[448]", "X": 1}, { "VarName": "z[449]", "X": 1}, { "VarName": "z[450]", "X": 1}, { "VarName": "z[451]", "X": 1}, { "VarName": "z[452]", "X": 1}, { "VarName": "z[453]", "X": 1}, { "VarName": "z[691]", "X": 1}, { "VarName": "z[692]", "X": 1}, { "VarName": "z[693]", "X": 1}, { "VarName": "z[694]", "X": 1}, { "VarName": "z[695]", "X": 1}, { "VarName": "z[696]", "X": 1}, { "VarName": "z[697]", "X": 1}, { "VarName": "z[698]", "X": 1}, { "VarName": "z[699]", "X": 1}, { "VarName": "z[700]", "X": 1}, { "VarName": "z[701]", "X": 1}, { "VarName": "z[702]", "X": 1}, { "VarName": "z[703]", "X": 1}, { "VarName": "z[704]", "X": 1}, { "VarName": "z[705]", "X": 1}, { "VarName": "z[706]", "X": 1}, { "VarName": "z[707]", "X": 1}, { "VarName": "z[708]", "X": 1}, { "VarName": "z[709]", "X": 1}, { "VarName": "z[710]", "X": 1}, { "VarName": "z[711]", "X": 1}, { "VarName": "z[712]", "X": 1}, { "VarName": "z[713]", "X": 1}, { "VarName": "z[714]", "X": 1}, { "VarName": "z[715]", "X": 1}, { "VarName": "z[716]", "X": 1}, { "VarName": "z[717]", "X": 1}, { "VarName": "z[718]", "X": 1}, { "VarName": "z[719]", "X": 1}, { "VarName": "z[720]", "X": 1}, { "VarName": "z[721]", "X": 1}, { "VarName": "z[722]", "X": 1}, { "VarName": "z[723]", "X": 1}, { "VarName": "z[724]", "X": 1}, { "VarName": "z[725]", "X": 1}, { "VarName": "z[726]", "X": 1}, { "VarName": "z[727]", "X": 1}, { "VarName": "z[728]", "X": 1}, { "VarName": "z[729]", "X": 1}, { "VarName": "z[730]", "X": 1}, { "VarName": "z[731]", "X": 1}, { "VarName": "z[732]", "X": 1}, { "VarName": "z[733]", "X": 1}, { "VarName": "z[734]", "X": 1}, { "VarName": "z[735]", "X": 1}, { "VarName": "z[736]", "X": 1}, { "VarName": "z[737]", "X": 1}, { "VarName": "z[738]", "X": 1}, { "VarName": "z[739]", "X": 1}, { "VarName": "z[740]", "X": 1}, { "VarName": "z[741]", "X": 1}, { "VarName": "z[742]", "X": 1}, { "VarName": "z[743]", "X": 1}, { "VarName": "z[744]", "X": 1}, { "VarName": "z[745]", "X": 1}, { "VarName": "z[746]", "X": 1}, { "VarName": "z[747]", "X": 1}, { "VarName": "z[748]", "X": 1}, { "VarName": "z[749]", "X": 1}, { "VarName": "z[750]", "X": 1}, { "VarName": "z[751]", "X": 1}, { "VarName": "z[752]", "X": 1}, { "VarName": "z[753]", "X": 1}, { "VarName": "z[754]", "X": 1}, { "VarName": "z[755]", "X": 1}, { "VarName": "z[756]", "X": 1}, { "VarName": "z[757]", "X": 1}, { "VarName": "z[758]", "X": 1}, { "VarName": "z[759]", "X": 1}, { "VarName": "z[760]", "X": 1}, { "VarName": "z[761]", "X": 1}, { "VarName": "z[762]", "X": 1}, { "VarName": "z[763]", "X": 1}, { "VarName": "z[764]", "X": 1}, { "VarName": "z[765]", "X": 1}, { "VarName": "z[766]", "X": 1}, { "VarName": "z[767]", "X": 1}, { "VarName": "z[768]", "X": 1}, { "VarName": "z[769]", "X": 1}, { "VarName": "z[770]", "X": 1}, { "VarName": "z[771]", "X": 1}, { "VarName": "z[772]", "X": 1}, { "VarName": "z[773]", "X": 1}, { "VarName": "z[774]", "X": 1}, { "VarName": "z[775]", "X": 1}, { "VarName": "z[1025]", "X": 1}, { "VarName": "z[1026]", "X": 1}, { "VarName": "z[1027]", "X": 1}, { "VarName": "z[1028]", "X": 1}, { "VarName": "z[1029]", "X": 1}, { "VarName": "z[1030]", "X": 1}, { "VarName": "z[1031]", "X": 1}, { "VarName": "z[1032]", "X": 1}, { "VarName": "z[1033]", "X": 1}, { "VarName": "z[1034]", "X": 1}, { "VarName": "z[1035]", "X": 1}, { "VarName": "z[1036]", "X": 1}, { "VarName": "z[1037]", "X": 1}, { "VarName": "z[1038]", "X": 1}, { "VarName": "z[1039]", "X": 1}, { "VarName": "z[1040]", "X": 1}, { "VarName": "z[1041]", "X": 1}, { "VarName": "z[1042]", "X": 1}, { "VarName": "z[1043]", "X": 1}, { "VarName": "z[1044]", "X": 1}, { "VarName": "z[1045]", "X": 1}, { "VarName": "z[1046]", "X": 1}, { "VarName": "z[1047]", "X": 1}, { "VarName": "z[1048]", "X": 1}, { "VarName": "z[1049]", "X": 1}, { "VarName": "z[1050]", "X": 1}, { "VarName": "z[1051]", "X": 1}, { "VarName": "z[1052]", "X": 1}, { "VarName": "z[1053]", "X": 1}, { "VarName": "z[1054]", "X": 1}, { "VarName": "z[1055]", "X": 1}, { "VarName": "z[1056]", "X": 1}, { "VarName": "z[1057]", "X": 1}, { "VarName": "z[1058]", "X": 1}, { "VarName": "z[1059]", "X": 1}, { "VarName": "z[1060]", "X": 1}, { "VarName": "z[1061]", "X": 1}, { "VarName": "z[1062]", "X": 1}, { "VarName": "z[1063]", "X": 1}, { "VarName": "z[1064]", "X": 1}, { "VarName": "z[1065]", "X": 1}, { "VarName": "z[1066]", "X": 1}, { "VarName": "z[1067]", "X": 1}, { "VarName": "z[1068]", "X": 1}, { "VarName": "z[1069]", "X": 1}, { "VarName": "z[1070]", "X": 1}, { "VarName": "z[1071]", "X": 1}, { "VarName": "z[1072]", "X": 1}, { "VarName": "z[1073]", "X": 1}, { "VarName": "z[1074]", "X": 1}, { "VarName": "z[1075]", "X": 1}, { "VarName": "z[1076]", "X": 1}, { "VarName": "z[1077]", "X": 1}, { "VarName": "z[1078]", "X": 1}, { "VarName": "z[1079]", "X": 1}, { "VarName": "z[1080]", "X": 1}, { "VarName": "z[1081]", "X": 1}, { "VarName": "z[1082]", "X": 1}, { "VarName": "z[1083]", "X": 1}, { "VarName": "z[1084]", "X": 1}, { "VarName": "z[1085]", "X": 1}, { "VarName": "z[1086]", "X": 1}, { "VarName": "z[1087]", "X": 1}, { "VarName": "z[1088]", "X": 1}, { "VarName": "z[1089]", "X": 1}, { "VarName": "z[1090]", "X": 1}, { "VarName": "z[1091]", "X": 1}, { "VarName": "z[1092]", "X": 1}, { "VarName": "z[1093]", "X": 1}, { "VarName": "z[1367]", "X": 1}, { "VarName": "z[1368]", "X": 1}, { "VarName": "z[1700]", "X": 1}, { "VarName": "z[1701]", "X": 1}, { "VarName": "z[1702]", "X": 1}, { "VarName": "z[1703]", "X": 1}, { "VarName": "z[1704]", "X": 1}, { "VarName": "z[1705]", "X": 1}, { "VarName": "z[1706]", "X": 1}, { "VarName": "z[1707]", "X": 1}, { "VarName": "z[1708]", "X": 1}, { "VarName": "z[1709]", "X": 1}, { "VarName": "z[1710]", "X": 1}, { "VarName": "z[1711]", "X": 1}, { "VarName": "z[1712]", "X": 1}, { "VarName": "z[1713]", "X": 1}, { "VarName": "z[1714]", "X": 1}, { "VarName": "z[1715]", "X": 1}, { "VarName": "z[1716]", "X": 1}, { "VarName": "z[1717]", "X": 1}, { "VarName": "z[1718]", "X": 1}, { "VarName": "z[1719]", "X": 1}, { "VarName": "z[1720]", "X": 1}, { "VarName": "z[1721]", "X": 1}, { "VarName": "z[1722]", "X": 1}, { "VarName": "z[1723]", "X": 1}, { "VarName": "z[1724]", "X": 1}, { "VarName": "z[1725]", "X": 1}, { "VarName": "z[1726]", "X": 1}, { "VarName": "z[1727]", "X": 1}, { "VarName": "z[1728]", "X": 1}, { "VarName": "z[1729]", "X": 1}, { "VarName": "z[1730]", "X": 1}, { "VarName": "z[1731]", "X": 1}, { "VarName": "z[1732]", "X": 1}, { "VarName": "z[1733]", "X": 1}, { "VarName": "z[1734]", "X": 1}, { "VarName": "z[1735]", "X": 1}, { "VarName": "z[1736]", "X": 1}, { "VarName": "z[1737]", "X": 1}, { "VarName": "z[1738]", "X": 1}, { "VarName": "z[1739]", "X": 1}, { "VarName": "z[1740]", "X": 1}, { "VarName": "z[1741]", "X": 1}, { "VarName": "z[1742]", "X": 1}, { "VarName": "z[1743]", "X": 1}, { "VarName": "z[1744]", "X": 1}, { "VarName": "z[2712]", "X": 1}]}